<?xml version="1.0" encoding="UTF-8"?>
<!--
  ~ Copyright (c) 2016. Axetta LLC. All Rights Reserved.
  -->

<!DOCTYPE hibernate-mapping PUBLIC "-//Hibernate/Hibernate Mapping DTD 3.0//EN"
        "http://www.hibernate.org/dtd/hibernate-mapping-3.0.dtd">
<hibernate-mapping>
    <class name="ru.axetta.ecafe.processor.core.persistence.MenuSupplier" table="cf_menu_suppliers">

        <id name="idOfMenuSupplier" column="idOfMenuSupplier" type="long">
            <generator class="hilo">
                <param name="table">CF_Generators</param>
                <param name="column">idOfMenuSupplier</param>
                <param name="max_lo">3</param>
            </generator>
        </id>

    </class>
</hibernate-mapping>


