<?xml version="1.0" encoding="UTF-8"?>

<persistence xmlns="http://java.sun.com/xml/ns/persistence" version="2.0">
    <persistence-unit name="client_room" transaction-type="RESOURCE_LOCAL">
        <provider>org.hibernate.ejb.HibernatePersistence</provider>
        <jta-data-source>java:jboss/ECafeClientRoomDS</jta-data-source>
        <properties>
            <property name="hibernate.dialect"
                      value="org.hibernate.dialect.PostgreSQLDialect"/>
            <property name="hibernate.show_sql" value="true"/>
            <property name="jboss.entity.manager.jndi.name" value="java:/clientRoomPU"/>
            <property name="jboss.entity.manager.factory.jndi.name" value="java:/clientRoomPUFactory"/>
        </properties>
    </persistence-unit>
</persistence>